{
    "record1": {
        "actor_loss": -1.619912647920847,
        "critic_loss": 1413.9359806396485,
        "reward_mean": -225.74593209228516
    },
    "record2": {
        "actor_loss": -1.7077694943398236,
        "critic_loss": 1374.4507236328125,
        "reward_mean": -226.25416138305664
    },
    "record3": {
        "actor_loss": -1.6660748310610651,
        "critic_loss": 1302.2957182861328,
        "reward_mean": -226.11386660461426
    },
    "record4": {
        "actor_loss": -1.4396930642157793,
        "critic_loss": 1314.4444198425292,
        "reward_mean": -232.42474447021485
    },
    "record5": {
        "actor_loss": -1.3223093072712422,
        "critic_loss": 1215.6134450500488,
        "reward_mean": -225.4565424987793
    },
    "record6": {
        "actor_loss": -1.7355979262411594,
        "critic_loss": 1245.7993901123048,
        "reward_mean": -223.29683415527344
    },
    "record7": {
        "actor_loss": -1.7739956012874842,
        "critic_loss": 1245.4935056274414,
        "reward_mean": -225.7181222808838
    },
    "record8": {
        "actor_loss": -1.810827262634039,
        "critic_loss": 1238.354323413086,
        "reward_mean": -227.8872336151123
    },
    "record9": {
        "actor_loss": -1.5619801934242248,
        "critic_loss": 1128.9488523315429,
        "reward_mean": -224.07442493286132
    },
    "record10": {
        "actor_loss": -1.2907636835113168,
        "critic_loss": 1094.9283659057617,
        "reward_mean": -221.04014522705077
    },
    "record11": {
        "actor_loss": -1.4356376622766256,
        "critic_loss": 1187.547012902832,
        "reward_mean": -224.624175289917
    },
    "record12": {
        "actor_loss": -1.5876583902180195,
        "critic_loss": 1197.911695690918,
        "reward_mean": -228.04750320129395
    },
    "record13": {
        "actor_loss": -1.0187119424015283,
        "critic_loss": 983.4575174743652,
        "reward_mean": -218.1919001739502
    },
    "record14": {
        "actor_loss": -0.8334872658863663,
        "critic_loss": 932.9393157104493,
        "reward_mean": -218.66897657470705
    },
    "record15": {
        "actor_loss": -1.4698685544088483,
        "critic_loss": 1195.7473644348145,
        "reward_mean": -227.27176362304687
    },
    "record16": {
        "actor_loss": -1.5576236846864224,
        "critic_loss": 1181.8623312866212,
        "reward_mean": -226.20763038330077
    },
    "record17": {
        "actor_loss": -1.2773638081163168,
        "critic_loss": 1007.5446418884277,
        "reward_mean": -223.88561003723146
    },
    "record18": {
        "actor_loss": -1.367030941967666,
        "critic_loss": 1022.3784641418457,
        "reward_mean": -222.94005238952636
    },
    "record19": {
        "actor_loss": -2.1370458125948906,
        "critic_loss": 1335.8375091918945,
        "reward_mean": -231.87423735961914
    },
    "record20": {
        "actor_loss": -1.9199030877113343,
        "critic_loss": 1258.9998458862306,
        "reward_mean": -228.32656668395995
    },
    "record21": {
        "actor_loss": -1.7988734522521497,
        "critic_loss": 1259.733631237793,
        "reward_mean": -226.42429760131836
    },
    "record22": {
        "actor_loss": -1.9041734902560712,
        "critic_loss": 1282.237639782715,
        "reward_mean": -228.60762092895507
    },
    "record23": {
        "actor_loss": -1.9455767385184766,
        "critic_loss": 1304.163032849121,
        "reward_mean": -229.63101816711426
    },
    "record24": {
        "actor_loss": -2.349029548740387,
        "critic_loss": 1479.8885442260741,
        "reward_mean": -231.78319416503905
    },
    "record25": {
        "actor_loss": -2.4250017528295515,
        "critic_loss": 1581.0160565551757,
        "reward_mean": -236.16593692626952
    },
    "record26": {
        "actor_loss": -2.489296933245659,
        "critic_loss": 1609.9888264160156,
        "reward_mean": -237.18230646362304
    },
    "record27": {
        "actor_loss": -2.2952973653912543,
        "critic_loss": 1543.8935581054689,
        "reward_mean": -232.83161038513182
    },
    "record28": {
        "actor_loss": -2.292661490428448,
        "critic_loss": 1533.426815185547,
        "reward_mean": -231.37354966430664
    },
    "record29": {
        "actor_loss": -2.466432850575447,
        "critic_loss": 1617.149141015625,
        "reward_mean": -238.7834389038086
    },
    "record30": {
        "actor_loss": -2.386490537428856,
        "critic_loss": 1473.9925725219728,
        "reward_mean": -234.20209468078613
    },
    "record31": {
        "actor_loss": -2.4720258479833603,
        "critic_loss": 1462.0275097045899,
        "reward_mean": -230.82923074035645
    },
    "record32": {
        "actor_loss": -2.3953580736398696,
        "critic_loss": 1458.451042578125,
        "reward_mean": -230.98553914794923
    },
    "record33": {
        "actor_loss": -2.3602389196634292,
        "critic_loss": 1447.2307483032228,
        "reward_mean": -233.25859829101563
    },
    "record34": {
        "actor_loss": -2.177475087916851,
        "critic_loss": 1350.6941952026368,
        "reward_mean": -225.53936296386718
    },
    "record35": {
        "actor_loss": -1.9095177770197391,
        "critic_loss": 1307.0245635131837,
        "reward_mean": -227.4128755859375
    },
    "record36": {
        "actor_loss": -1.979230421590805,
        "critic_loss": 1310.6972829101562,
        "reward_mean": -224.94508866271974
    },
    "record37": {
        "actor_loss": -2.2391423320412636,
        "critic_loss": 1413.2516241821288,
        "reward_mean": -224.7852181121826
    },
    "record38": {
        "actor_loss": -2.0472263454914095,
        "critic_loss": 1372.82148359375,
        "reward_mean": -223.4551028289795
    },
    "record39": {
        "actor_loss": -2.040233378648758,
        "critic_loss": 1333.1169020141601,
        "reward_mean": -225.49584767456054
    },
    "record40": {
        "actor_loss": -2.172069850754738,
        "critic_loss": 1430.7542016235352,
        "reward_mean": -230.2134740234375
    },
    "record41": {
        "actor_loss": -2.0879812985301016,
        "critic_loss": 1360.246849621582,
        "reward_mean": -228.05892444458007
    },
    "record42": {
        "actor_loss": -1.537129919013381,
        "critic_loss": 1112.9306059570313,
        "reward_mean": -221.92547922668456
    },
    "record43": {
        "actor_loss": -1.7864359687566758,
        "critic_loss": 1202.8483659790038,
        "reward_mean": -228.24283889160156
    },
    "record44": {
        "actor_loss": -2.2002320778727533,
        "critic_loss": 1317.626665661621,
        "reward_mean": -232.7232903289795
    },
    "record45": {
        "actor_loss": -2.229393824672699,
        "critic_loss": 1259.758080822754,
        "reward_mean": -233.80584650268554
    },
    "record46": {
        "actor_loss": -2.0812762892246246,
        "critic_loss": 1193.500380847168,
        "reward_mean": -238.88473620910645
    },
    "record47": {
        "actor_loss": -1.9187800242602826,
        "critic_loss": 1160.8948690063476,
        "reward_mean": -237.5716164428711
    },
    "record48": {
        "actor_loss": -2.104447269487381,
        "critic_loss": 1223.9761337890625,
        "reward_mean": -239.68777047729492
    },
    "record49": {
        "actor_loss": -2.059093752038479,
        "critic_loss": 1283.3542694946289,
        "reward_mean": -237.868653036499
    },
    "record50": {
        "actor_loss": -2.310535008454323,
        "critic_loss": 1468.0268045410157,
        "reward_mean": -237.13311511535645
    },
    "record51": {
        "actor_loss": -2.398031908106804,
        "critic_loss": 1481.776533935547,
        "reward_mean": -231.70809446411133
    },
    "record52": {
        "actor_loss": -2.2519976069808005,
        "critic_loss": 1392.813720263672,
        "reward_mean": -233.99521058959962
    },
    "record53": {
        "actor_loss": -2.163443330848217,
        "critic_loss": 1296.0855987426758,
        "reward_mean": -229.59073069763184
    },
    "record54": {
        "actor_loss": -2.242915705001354,
        "critic_loss": 1260.5192281738282,
        "reward_mean": -234.31320092773439
    },
    "record55": {
        "actor_loss": -2.2148672013044357,
        "critic_loss": 1286.4244718872071,
        "reward_mean": -235.79819597473144
    },
    "record56": {
        "actor_loss": -2.327984849834442,
        "critic_loss": 1364.0273130004882,
        "reward_mean": -230.12582704162597
    },
    "record57": {
        "actor_loss": -2.416264062643051,
        "critic_loss": 1400.5415336914064,
        "reward_mean": -229.16728392944336
    },
    "record58": {
        "actor_loss": -2.2652799436450004,
        "critic_loss": 1303.5027121826172,
        "reward_mean": -233.76032882385255
    },
    "record59": {
        "actor_loss": -2.039205913209915,
        "critic_loss": 1186.6547896240234,
        "reward_mean": -234.09797606811523
    },
    "record60": {
        "actor_loss": -2.1022219573140144,
        "critic_loss": 1259.1615918701173,
        "reward_mean": -229.26772290039062
    },
    "record61": {
        "actor_loss": -2.335536091375351,
        "critic_loss": 1441.3195832641602,
        "reward_mean": -228.34860072631835
    },
    "record62": {
        "actor_loss": -2.272335289478302,
        "critic_loss": 1379.1271920532226,
        "reward_mean": -231.66867322692872
    },
    "record63": {
        "actor_loss": -2.0272920193195345,
        "critic_loss": 1233.1016903686523,
        "reward_mean": -234.61526864013672
    },
    "record64": {
        "actor_loss": -1.6333505916416644,
        "critic_loss": 1131.1031398803711,
        "reward_mean": -234.08943694152833
    },
    "record65": {
        "actor_loss": -1.7013079060465097,
        "critic_loss": 1127.6850798828125,
        "reward_mean": -239.61611922607423
    },
    "record66": {
        "actor_loss": -1.8448668623238802,
        "critic_loss": 1185.7784055419922,
        "reward_mean": -229.82352989807129
    },
    "record67": {
        "actor_loss": -2.126767155003548,
        "critic_loss": 1267.264153894043,
        "reward_mean": -233.18835108947755
    },
    "record68": {
        "actor_loss": -2.264804239356518,
        "critic_loss": 1337.945665197754,
        "reward_mean": -233.96720432128907
    },
    "record69": {
        "actor_loss": -1.941904316496849,
        "critic_loss": 1192.3596993652343,
        "reward_mean": -233.2192327911377
    },
    "record70": {
        "actor_loss": -1.8013267019093038,
        "critic_loss": 1174.4844563537597,
        "reward_mean": -232.5851984588623
    },
    "record71": {
        "actor_loss": -2.1145186378002165,
        "critic_loss": 1340.3565879882813,
        "reward_mean": -233.10507387084962
    },
    "record72": {
        "actor_loss": -2.137423599088192,
        "critic_loss": 1351.3508993164062,
        "reward_mean": -233.38078302001952
    },
    "record73": {
        "actor_loss": -2.152637908554077,
        "critic_loss": 1351.5450498046876,
        "reward_mean": -230.5634012664795
    },
    "record74": {
        "actor_loss": -2.3023830456733703,
        "critic_loss": 1467.5770935424805,
        "reward_mean": -232.66477117309572
    },
    "record75": {
        "actor_loss": -2.3261056296110154,
        "critic_loss": 1490.9553166870116,
        "reward_mean": -234.7811059387207
    },
    "record76": {
        "actor_loss": -2.0083737812295555,
        "critic_loss": 1411.476424255371,
        "reward_mean": -228.51414765625
    },
    "record77": {
        "actor_loss": -2.297031850540638,
        "critic_loss": 1475.296706555176,
        "reward_mean": -227.77595174560548
    },
    "record78": {
        "actor_loss": -2.388379838871956,
        "critic_loss": 1528.2610651000978,
        "reward_mean": -229.81074566040039
    },
    "record79": {
        "actor_loss": -2.262613810586929,
        "critic_loss": 1502.5628324096679,
        "reward_mean": -228.02914977111817
    },
    "record80": {
        "actor_loss": -2.413211294937134,
        "critic_loss": 1561.860194580078,
        "reward_mean": -228.78927624206543
    },
    "record81": {
        "actor_loss": -2.5315345770835878,
        "critic_loss": 1618.3418459960938,
        "reward_mean": -230.2845588897705
    },
    "record82": {
        "actor_loss": -2.518869689130783,
        "critic_loss": 1634.7285823242187,
        "reward_mean": -230.76695725708007
    },
    "record83": {
        "actor_loss": -2.3333212927222253,
        "critic_loss": 1496.8443039550782,
        "reward_mean": -225.28886177978515
    },
    "record84": {
        "actor_loss": -2.251163714039326,
        "critic_loss": 1448.5957400512696,
        "reward_mean": -229.26597494506836
    },
    "record85": {
        "actor_loss": -2.308056259524822,
        "critic_loss": 1510.6991521484374,
        "reward_mean": -233.37240955810546
    },
    "record86": {
        "actor_loss": -2.312061117720604,
        "critic_loss": 1502.4314904174805,
        "reward_mean": -237.64586114501952
    },
    "record87": {
        "actor_loss": -2.143167261791229,
        "critic_loss": 1425.73921328125,
        "reward_mean": -226.91554772949218
    },
    "record88": {
        "actor_loss": -2.28023751668334,
        "critic_loss": 1501.485723034668,
        "reward_mean": -227.79722653198243
    },
    "record89": {
        "actor_loss": -2.3575161483049394,
        "critic_loss": 1552.2286399047853,
        "reward_mean": -232.17512436523438
    },
    "record90": {
        "actor_loss": -2.4269944383859636,
        "critic_loss": 1581.4025369628907,
        "reward_mean": -232.42638666687012
    },
    "record91": {
        "actor_loss": -2.3812345010757445,
        "critic_loss": 1501.4479041259765,
        "reward_mean": -235.1712138885498
    },
    "record92": {
        "actor_loss": -2.249041168487072,
        "critic_loss": 1386.5777666625977,
        "reward_mean": -242.48074888000488
    },
    "record93": {
        "actor_loss": -2.24433502471447,
        "critic_loss": 1394.1466974731445,
        "reward_mean": -237.4025320678711
    },
    "record94": {
        "actor_loss": -2.1635021688103677,
        "critic_loss": 1340.2270692993163,
        "reward_mean": -240.3802857696533
    },
    "record95": {
        "actor_loss": -1.9435926474094392,
        "critic_loss": 1228.54440390625,
        "reward_mean": -241.82026717224122
    },
    "record96": {
        "actor_loss": -2.08651589730978,
        "critic_loss": 1257.4828247192384,
        "reward_mean": -243.5572377532959
    },
    "record97": {
        "actor_loss": -2.15921839799881,
        "critic_loss": 1313.8747235229491,
        "reward_mean": -241.93417499389648
    },
    "record98": {
        "actor_loss": -2.239332183253765,
        "critic_loss": 1323.9491229614257,
        "reward_mean": -239.96169303588866
    },
    "record99": {
        "actor_loss": -2.175945920741558,
        "critic_loss": 1279.6327140991211,
        "reward_mean": -240.39043275146486
    },
    "record100": {
        "actor_loss": -2.3812263271331786,
        "critic_loss": 1430.908858630371,
        "reward_mean": -236.06440151367187
    }
}